openweather/__init__.py
openweather/client.py
openweather/endpoints.py
openweather/exceptions.py
openweather/models.py
openweather/utils.py
sync_openweatherapi_python_sdk-0.1.2.dist-info/licenses/LICENSE
sync_openweatherapi_python_sdk-0.1.2.dist-info/METADATA
sync_openweatherapi_python_sdk-0.1.2.dist-info/WHEEL
sync_openweatherapi_python_sdk-0.1.2.dist-info/top_level.txt
sync_openweatherapi_python_sdk-0.1.2.dist-info/RECORD
