Metadata-Version: 2.4
Name: sync_openweatherapi_python_sdk
Version: 0.1.2
Summary: Sync-only Python SDK for OpenWeatherMap (base pattern)
Author: Nitin S Kulkarni
License: MIT
Project-URL: Homepage, https://github.com/nkpythondeveloper/sync_openweatherapi_python_sdk
Project-URL: Issues, https://github.com/nkpythondeveloper/sync_openweatherapi_python_sdk/issues
Keywords: openweathermap,sdk,weather
Classifier: Programming Language :: Python :: 3
Classifier: License :: OSI Approved :: MIT License
Classifier: Operating System :: OS Independent
Requires-Python: >=3.9
License-File: LICENSE
Requires-Dist: requests>=2.31
Requires-Dist: pydantic>=2.7
Provides-Extra: dev
Requires-Dist: pytest>=8; extra == "dev"
Requires-Dist: responses>=0.25; extra == "dev"
Requires-Dist: ruff>=0.6; extra == "dev"
Requires-Dist: mypy>=1.11; extra == "dev"
Requires-Dist: python-dotenv>=1.0; extra == "dev"
Requires-Dist: types-requests>=2.32; extra == "dev"
Dynamic: license-file
